{
  "model": {
    "id": "hybrid",
    "name": "Hybrid",
    "version": "1.0",
    "generated_at": "2026-07-11T12:09:08.660026+00:00",
    "weights": {
      "j5l": 0.35,
      "dt": 0.25,
      "kalshi": 0.4
    },
    "method": "Equal 1/3 blend of J5L composite + DT rating + Kalshi implied strength; bivariate-Poisson Monte-Carlo of the 48-team/12-group bracket.",
    "note": "Group bars blend \u2153 each at the match level, using REAL per-match Kalshi odds (KXWCGAME) where priced and tournament-winner strength otherwise. Champion odds use the blended strength. Recomputed each data refresh."
  },
  "bracket_simulation": {
    "iterations": 20000,
    "seed": 2026
  },
  "teams": [
    {
      "rank": 1,
      "team": "Spain",
      "champion": 0.2868,
      "final": 0.5252,
      "sf": 0.8054,
      "qf": 0.8965,
      "r16": 0.9557,
      "r32": 1.0,
      "hybrid_strength": 2.676
    },
    {
      "rank": 2,
      "team": "France",
      "champion": 0.2439,
      "final": 0.4311,
      "sf": 0.7099,
      "qf": 0.8912,
      "r16": 0.9526,
      "r32": 0.9992,
      "hybrid_strength": 2.685
    },
    {
      "rank": 3,
      "team": "England",
      "champion": 0.2354,
      "final": 0.4471,
      "sf": 0.8146,
      "qf": 0.8964,
      "r16": 0.951,
      "r32": 0.9996,
      "hybrid_strength": 2.528
    },
    {
      "rank": 4,
      "team": "Argentina",
      "champion": 0.1918,
      "final": 0.4008,
      "sf": 0.7882,
      "qf": 0.8739,
      "r16": 0.9376,
      "r32": 0.9999,
      "hybrid_strength": 2.363
    },
    {
      "rank": 5,
      "team": "Norway",
      "champion": 0.0274,
      "final": 0.0866,
      "sf": 0.2292,
      "qf": 0.7154,
      "r16": 0.8434,
      "r32": 0.969,
      "hybrid_strength": 1.67
    },
    {
      "rank": 6,
      "team": "Switzerland",
      "champion": 0.0069,
      "final": 0.0318,
      "sf": 0.1135,
      "qf": 0.5573,
      "r16": 0.753,
      "r32": 0.9814,
      "hybrid_strength": 1.004
    },
    {
      "rank": 7,
      "team": "Netherlands",
      "champion": 0.0022,
      "final": 0.0167,
      "sf": 0.0906,
      "qf": 0.4536,
      "r16": 0.6609,
      "r32": 0.9218,
      "hybrid_strength": 0.672
    },
    {
      "rank": 8,
      "team": "Portugal",
      "champion": 0.0022,
      "final": 0.0171,
      "sf": 0.0891,
      "qf": 0.4788,
      "r16": 0.6865,
      "r32": 0.9348,
      "hybrid_strength": 0.783
    },
    {
      "rank": 9,
      "team": "Germany",
      "champion": 0.0006,
      "final": 0.0056,
      "sf": 0.0333,
      "qf": 0.1384,
      "r16": 0.6701,
      "r32": 0.9504,
      "hybrid_strength": 0.55
    },
    {
      "rank": 10,
      "team": "Brazil",
      "champion": 0.0006,
      "final": 0.0056,
      "sf": 0.0318,
      "qf": 0.0767,
      "r16": 0.6581,
      "r32": 0.9306,
      "hybrid_strength": 0.486
    },
    {
      "rank": 11,
      "team": "Morocco",
      "champion": 0.0003,
      "final": 0.0029,
      "sf": 0.0243,
      "qf": 0.124,
      "r16": 0.6378,
      "r32": 0.8912,
      "hybrid_strength": 0.285
    },
    {
      "rank": 12,
      "team": "Belgium",
      "champion": 0.0003,
      "final": 0.004,
      "sf": 0.0356,
      "qf": 0.0703,
      "r16": 0.6468,
      "r32": 0.9365,
      "hybrid_strength": 0.29
    },
    {
      "rank": 13,
      "team": "Croatia",
      "champion": 0.0003,
      "final": 0.0032,
      "sf": 0.0203,
      "qf": 0.1773,
      "r16": 0.5924,
      "r32": 0.8075,
      "hybrid_strength": 0.253
    },
    {
      "rank": 14,
      "team": "Bosnia and Herzegovina",
      "champion": 0.0003,
      "final": 0.0034,
      "sf": 0.0301,
      "qf": 0.2772,
      "r16": 0.6802,
      "r32": 0.8712,
      "hybrid_strength": 0.188
    },
    {
      "rank": 15,
      "team": "Japan",
      "champion": 0.0003,
      "final": 0.0029,
      "sf": 0.0246,
      "qf": 0.2233,
      "r16": 0.6082,
      "r32": 0.8039,
      "hybrid_strength": 0.206
    },
    {
      "rank": 16,
      "team": "Czechia",
      "champion": 0.0001,
      "final": 0.0034,
      "sf": 0.0262,
      "qf": 0.0585,
      "r16": 0.6182,
      "r32": 0.9102,
      "hybrid_strength": 0.299
    },
    {
      "rank": 17,
      "team": "Colombia",
      "champion": 0.0001,
      "final": 0.0027,
      "sf": 0.0234,
      "qf": 0.1839,
      "r16": 0.4411,
      "r32": 0.7752,
      "hybrid_strength": 0.147
    },
    {
      "rank": 18,
      "team": "DR Congo",
      "champion": 0.0001,
      "final": 0.0015,
      "sf": 0.0135,
      "qf": 0.0844,
      "r16": 0.1978,
      "r32": 0.7486,
      "hybrid_strength": 0.079
    },
    {
      "rank": 19,
      "team": "Uruguay",
      "champion": 0.0001,
      "final": 0.0006,
      "sf": 0.0056,
      "qf": 0.0386,
      "r16": 0.0835,
      "r32": 0.7721,
      "hybrid_strength": -0.108
    },
    {
      "rank": 20,
      "team": "Korea Republic",
      "champion": 0.0001,
      "final": 0.0003,
      "sf": 0.0066,
      "qf": 0.0619,
      "r16": 0.215,
      "r32": 0.7542,
      "hybrid_strength": -0.231
    },
    {
      "rank": 21,
      "team": "Canada",
      "champion": 0.0001,
      "final": 0.0001,
      "sf": 0.0032,
      "qf": 0.0165,
      "r16": 0.2037,
      "r32": 0.6578,
      "hybrid_strength": -0.384
    },
    {
      "rank": 22,
      "team": "Senegal",
      "champion": 0.0001,
      "final": 0.0011,
      "sf": 0.0095,
      "qf": 0.0692,
      "r16": 0.1613,
      "r32": 0.4358,
      "hybrid_strength": 0.103
    },
    {
      "rank": 23,
      "team": "Austria",
      "champion": 0.0001,
      "final": 0.0006,
      "sf": 0.0077,
      "qf": 0.042,
      "r16": 0.0994,
      "r32": 0.7655,
      "hybrid_strength": 0.031
    },
    {
      "rank": 24,
      "team": "Scotland",
      "champion": 0.0,
      "final": 0.0001,
      "sf": 0.003,
      "qf": 0.0298,
      "r16": 0.2102,
      "r32": 0.6947,
      "hybrid_strength": -0.331
    },
    {
      "rank": 25,
      "team": "Turkiye",
      "champion": 0.0,
      "final": 0.0008,
      "sf": 0.0083,
      "qf": 0.0355,
      "r16": 0.0724,
      "r32": 0.8351,
      "hybrid_strength": 0.015
    },
    {
      "rank": 26,
      "team": "Paraguay",
      "champion": 0.0,
      "final": 0.0003,
      "sf": 0.0012,
      "qf": 0.0184,
      "r16": 0.1414,
      "r32": 0.5159,
      "hybrid_strength": -0.722
    },
    {
      "rank": 27,
      "team": "Australia",
      "champion": 0.0,
      "final": 0.0,
      "sf": 0.0018,
      "qf": 0.0173,
      "r16": 0.1605,
      "r32": 0.5763,
      "hybrid_strength": -0.629
    },
    {
      "rank": 28,
      "team": "USA",
      "champion": 0.0,
      "final": 0.0012,
      "sf": 0.0094,
      "qf": 0.0328,
      "r16": 0.072,
      "r32": 0.8418,
      "hybrid_strength": 0.031
    },
    {
      "rank": 29,
      "team": "Haiti",
      "champion": 0.0,
      "final": 0.0,
      "sf": 0.0003,
      "qf": 0.0075,
      "r16": 0.0465,
      "r32": 0.2386,
      "hybrid_strength": -1.18
    },
    {
      "rank": 30,
      "team": "South Africa",
      "champion": 0.0,
      "final": 0.0,
      "sf": 0.0003,
      "qf": 0.0093,
      "r16": 0.0688,
      "r32": 0.3211,
      "hybrid_strength": -1.069
    },
    {
      "rank": 31,
      "team": "Qatar",
      "champion": 0.0,
      "final": 0.0,
      "sf": 0.0001,
      "qf": 0.0059,
      "r16": 0.0383,
      "r32": 0.2014,
      "hybrid_strength": -1.274
    },
    {
      "rank": 32,
      "team": "Mexico",
      "champion": 0.0,
      "final": 0.0003,
      "sf": 0.0062,
      "qf": 0.0746,
      "r16": 0.1598,
      "r32": 0.7896,
      "hybrid_strength": -0.151
    },
    {
      "rank": 33,
      "team": "Saudi Arabia",
      "champion": 0.0,
      "final": 0.0001,
      "sf": 0.0002,
      "qf": 0.0073,
      "r16": 0.0551,
      "r32": 0.2769,
      "hybrid_strength": -1.111
    },
    {
      "rank": 34,
      "team": "Cabo Verde",
      "champion": 0.0,
      "final": 0.0,
      "sf": 0.0004,
      "qf": 0.0119,
      "r16": 0.0831,
      "r32": 0.3572,
      "hybrid_strength": -0.951
    },
    {
      "rank": 35,
      "team": "Egypt",
      "champion": 0.0,
      "final": 0.0003,
      "sf": 0.0034,
      "qf": 0.0182,
      "r16": 0.224,
      "r32": 0.7397,
      "hybrid_strength": -0.463
    },
    {
      "rank": 36,
      "team": "New Zealand",
      "champion": 0.0,
      "final": 0.0,
      "sf": 0.0004,
      "qf": 0.0112,
      "r16": 0.077,
      "r32": 0.3824,
      "hybrid_strength": -1.16
    },
    {
      "rank": 37,
      "team": "Iran",
      "champion": 0.0,
      "final": 0.0001,
      "sf": 0.0016,
      "qf": 0.0185,
      "r16": 0.2064,
      "r32": 0.6939,
      "hybrid_strength": -0.576
    },
    {
      "rank": 38,
      "team": "Cote d'Ivoire",
      "champion": 0.0,
      "final": 0.0006,
      "sf": 0.0056,
      "qf": 0.0595,
      "r16": 0.1245,
      "r32": 0.7995,
      "hybrid_strength": -0.125
    },
    {
      "rank": 39,
      "team": "Tunisia",
      "champion": 0.0,
      "final": 0.0001,
      "sf": 0.001,
      "qf": 0.0124,
      "r16": 0.1065,
      "r32": 0.3886,
      "hybrid_strength": -0.67
    },
    {
      "rank": 40,
      "team": "Sweden",
      "champion": 0.0,
      "final": 0.0003,
      "sf": 0.0059,
      "qf": 0.063,
      "r16": 0.1696,
      "r32": 0.6441,
      "hybrid_strength": -0.189
    },
    {
      "rank": 41,
      "team": "Ecuador",
      "champion": 0.0,
      "final": 0.001,
      "sf": 0.0073,
      "qf": 0.0775,
      "r16": 0.1784,
      "r32": 0.7759,
      "hybrid_strength": -0.182
    },
    {
      "rank": 42,
      "team": "Curacao",
      "champion": 0.0,
      "final": 0.0,
      "sf": 0.0001,
      "qf": 0.0069,
      "r16": 0.0431,
      "r32": 0.2371,
      "hybrid_strength": -1.265
    },
    {
      "rank": 43,
      "team": "Iraq",
      "champion": 0.0,
      "final": 0.0,
      "sf": 0.0003,
      "qf": 0.0034,
      "r16": 0.0316,
      "r32": 0.1067,
      "hybrid_strength": -0.683
    },
    {
      "rank": 44,
      "team": "Algeria",
      "champion": 0.0,
      "final": 0.0004,
      "sf": 0.0037,
      "qf": 0.0362,
      "r16": 0.1777,
      "r32": 0.6186,
      "hybrid_strength": -0.299
    },
    {
      "rank": 45,
      "team": "Jordan",
      "champion": 0.0,
      "final": 0.0,
      "sf": 0.0001,
      "qf": 0.0043,
      "r16": 0.028,
      "r32": 0.1533,
      "hybrid_strength": -1.275
    },
    {
      "rank": 46,
      "team": "Uzbekistan",
      "champion": 0.0,
      "final": 0.0,
      "sf": 0.0007,
      "qf": 0.0115,
      "r16": 0.0792,
      "r32": 0.2979,
      "hybrid_strength": -0.816
    },
    {
      "rank": 47,
      "team": "Ghana",
      "champion": 0.0,
      "final": 0.0001,
      "sf": 0.0024,
      "qf": 0.0168,
      "r16": 0.1562,
      "r32": 0.52,
      "hybrid_strength": -0.382
    },
    {
      "rank": 48,
      "team": "Panama",
      "champion": 0.0,
      "final": 0.0,
      "sf": 0.0001,
      "qf": 0.0052,
      "r16": 0.0354,
      "r32": 0.1774,
      "hybrid_strength": -1.116
    }
  ]
}
