{
  "__meta__": {
    "updated_at": "2026-07-18T17:17:28+00:00",
    "source": "espn-team-injuries+api-football",
    "espn_entries": 0,
    "apifootball_entries": 0,
    "apifootball_updated_at": "2026-07-18T17:17:28+00:00",
    "apifootball_status": "ok",
    "note": "ESPN exposes no World Cup injury data; injuries/suspensions come from API-Football when APIFOOTBALL_KEY is set. Suspensions are also surfaced from match_events. See docs/APIFOOTBALL_INTEGRATION.md."
  },
  "by_team": {},
  "count": 0
}
